{
  "COLUMNS": [
    "YEAR",
    "COUNTDATE",
    "FISHCOUNT",
    "SPECIESID",
    "COUNTLOCATIONID",
    "COUNTLOCATION",
    "SPECIES"
  ],
  "DATA": [
    [
      2010,
      "2010-07-30",
      50,
      440,
      2003,
      "Litnik",
      "Coho"
    ],
    [
      2010,
      "2010-07-31",
      5,
      440,
      2003,
      "Litnik",
      "Coho"
    ],
    [
      2010,
      "2010-08-01",
      0,
      440,
      2003,
      "Litnik",
      "Coho"
    ],
    [
      2010,
      "2010-08-02",
      2,
      440,
      2003,
      "Litnik",
      "Coho"
    ],
    [
      2010,
      "2010-08-03",
      0,
      440,
      2003,
      "Litnik",
      "Coho"
    ],
    [
      2010,
      "2010-08-04",
      24,
      440,
      2003,
      "Litnik",
      "Coho"
    ],
    [
      2010,
      "2010-08-05",
      14,
      440,
      2003,
      "Litnik",
      "Coho"
    ],
    [
      2010,
      "2010-08-06",
      45,
      440,
      2003,
      "Litnik",
      "Coho"
    ],
    [
      2010,
      "2010-08-07",
      7,
      440,
      2003,
      "Litnik",
      "Coho"
    ],
    [
      2010,
      "2010-08-08",
      259,
      440,
      2003,
      "Litnik",
      "Coho"
    ],
    [
      2010,
      "2010-08-09",
      56,
      440,
      2003,
      "Litnik",
      "Coho"
    ],
    [
      2010,
      "2010-08-10",
      21,
      440,
      2003,
      "Litnik",
      "Coho"
    ],
    [
      2010,
      "2010-08-11",
      19,
      440,
      2003,
      "Litnik",
      "Coho"
    ],
    [
      2010,
      "2010-08-12",
      306,
      440,
      2003,
      "Litnik",
      "Coho"
    ],
    [
      2010,
      "2010-08-13",
      1,
      440,
      2003,
      "Litnik",
      "Coho"
    ],
    [
      2010,
      "2010-08-14",
      0,
      440,
      2003,
      "Litnik",
      "Coho"
    ],
    [
      2010,
      "2010-08-15",
      2022,
      440,
      2003,
      "Litnik",
      "Coho"
    ],
    [
      2010,
      "2010-08-16",
      286,
      440,
      2003,
      "Litnik",
      "Coho"
    ],
    [
      2010,
      "2010-08-17",
      532,
      440,
      2003,
      "Litnik",
      "Coho"
    ],
    [
      2010,
      "2010-08-18",
      242,
      440,
      2003,
      "Litnik",
      "Coho"
    ],
    [
      2010,
      "2010-08-19",
      35,
      440,
      2003,
      "Litnik",
      "Coho"
    ],
    [
      2010,
      "2010-08-20",
      8,
      440,
      2003,
      "Litnik",
      "Coho"
    ],
    [
      2010,
      "2010-08-21",
      179,
      440,
      2003,
      "Litnik",
      "Coho"
    ],
    [
      2010,
      "2010-08-22",
      631,
      440,
      2003,
      "Litnik",
      "Coho"
    ],
    [
      2010,
      "2010-08-23",
      0,
      440,
      2003,
      "Litnik",
      "Coho"
    ],
    [
      2010,
      "2010-08-24",
      14,
      440,
      2003,
      "Litnik",
      "Coho"
    ],
    [
      2010,
      "2010-08-25",
      48,
      440,
      2003,
      "Litnik",
      "Coho"
    ],
    [
      2010,
      "2010-08-26",
      590,
      440,
      2003,
      "Litnik",
      "Coho"
    ],
    [
      2010,
      "2010-08-27",
      124,
      440,
      2003,
      "Litnik",
      "Coho"
    ],
    [
      2010,
      "2010-08-28",
      118,
      440,
      2003,
      "Litnik",
      "Coho"
    ],
    [
      2010,
      "2010-08-29",
      241,
      440,
      2003,
      "Litnik",
      "Coho"
    ],
    [
      2010,
      "2010-08-30",
      26,
      440,
      2003,
      "Litnik",
      "Coho"
    ],
    [
      2010,
      "2010-08-31",
      33,
      440,
      2003,
      "Litnik",
      "Coho"
    ],
    [
      2010,
      "2010-09-01",
      7,
      440,
      2003,
      "Litnik",
      "Coho"
    ],
    [
      2010,
      "2010-09-02",
      2,
      440,
      2003,
      "Litnik",
      "Coho"
    ],
    [
      2010,
      "2010-09-03",
      20,
      440,
      2003,
      "Litnik",
      "Coho"
    ],
    [
      2010,
      "2010-09-04",
      162,
      440,
      2003,
      "Litnik",
      "Coho"
    ],
    [
      2010,
      "2010-09-05",
      2492,
      440,
      2003,
      "Litnik",
      "Coho"
    ],
    [
      2010,
      "2010-09-06",
      167,
      440,
      2003,
      "Litnik",
      "Coho"
    ],
    [
      2010,
      "2010-09-07",
      1500,
      440,
      2003,
      "Litnik",
      "Coho"
    ]
  ],
  "metadata": {
    "location_id": 2003,
    "species_id": "440",
    "year": "2010",
    "totalRecords": 40,
    "totalCount": 10288,
    "source": "SASAP",
    "last_updated": "2025-10-02T17:53:46.902599"
  }
}