{
  "COLUMNS": [
    "YEAR",
    "COUNTDATE",
    "FISHCOUNT",
    "SPECIESID",
    "COUNTLOCATIONID",
    "COUNTLOCATION",
    "SPECIES"
  ],
  "DATA": [
    [
      2013,
      "2013-07-26",
      1,
      450,
      2110,
      "Speel Lake",
      "Chum"
    ],
    [
      2013,
      "2013-09-09",
      1,
      450,
      2110,
      "Speel Lake",
      "Chum"
    ]
  ],
  "metadata": {
    "location_id": 2110,
    "species_id": "450",
    "year": "2013",
    "totalRecords": 2,
    "totalCount": 2,
    "source": "SASAP",
    "last_updated": "2025-10-02T17:53:42.489782"
  }
}