{
  "COLUMNS": [
    "YEAR",
    "COUNTDATE",
    "FISHCOUNT",
    "SPECIESID",
    "COUNTLOCATIONID",
    "COUNTLOCATION",
    "SPECIES"
  ],
  "DATA": [
    [
      1996,
      "1996-09-11",
      4,
      470,
      2005,
      "Buskin River",
      "Steelhead Up"
    ],
    [
      1996,
      "1996-09-12",
      0,
      470,
      2005,
      "Buskin River",
      "Steelhead Up"
    ],
    [
      1996,
      "1996-09-13",
      0,
      470,
      2005,
      "Buskin River",
      "Steelhead Up"
    ],
    [
      1996,
      "1996-09-14",
      0,
      470,
      2005,
      "Buskin River",
      "Steelhead Up"
    ],
    [
      1996,
      "1996-09-15",
      0,
      470,
      2005,
      "Buskin River",
      "Steelhead Up"
    ],
    [
      1996,
      "1996-09-16",
      0,
      470,
      2005,
      "Buskin River",
      "Steelhead Up"
    ],
    [
      1996,
      "1996-09-17",
      0,
      470,
      2005,
      "Buskin River",
      "Steelhead Up"
    ],
    [
      1996,
      "1996-09-18",
      0,
      470,
      2005,
      "Buskin River",
      "Steelhead Up"
    ],
    [
      1996,
      "1996-09-19",
      0,
      470,
      2005,
      "Buskin River",
      "Steelhead Up"
    ],
    [
      1996,
      "1996-09-20",
      0,
      470,
      2005,
      "Buskin River",
      "Steelhead Up"
    ],
    [
      1996,
      "1996-09-21",
      0,
      470,
      2005,
      "Buskin River",
      "Steelhead Up"
    ],
    [
      1996,
      "1996-09-22",
      6,
      470,
      2005,
      "Buskin River",
      "Steelhead Up"
    ],
    [
      1996,
      "1996-09-23",
      0,
      470,
      2005,
      "Buskin River",
      "Steelhead Up"
    ],
    [
      1996,
      "1996-09-24",
      0,
      470,
      2005,
      "Buskin River",
      "Steelhead Up"
    ],
    [
      1996,
      "1996-09-25",
      0,
      470,
      2005,
      "Buskin River",
      "Steelhead Up"
    ],
    [
      1996,
      "1996-09-26",
      0,
      470,
      2005,
      "Buskin River",
      "Steelhead Up"
    ],
    [
      1996,
      "1996-09-27",
      0,
      470,
      2005,
      "Buskin River",
      "Steelhead Up"
    ],
    [
      1996,
      "1996-09-28",
      0,
      470,
      2005,
      "Buskin River",
      "Steelhead Up"
    ],
    [
      1996,
      "1996-09-29",
      0,
      470,
      2005,
      "Buskin River",
      "Steelhead Up"
    ],
    [
      1996,
      "1996-09-30",
      0,
      470,
      2005,
      "Buskin River",
      "Steelhead Up"
    ]
  ],
  "metadata": {
    "location_id": 2005,
    "species_id": "470",
    "year": "1996",
    "totalRecords": 20,
    "totalCount": 10,
    "source": "SASAP",
    "last_updated": "2025-10-02T17:53:45.734518"
  }
}