{
  "COLUMNS": [
    "YEAR",
    "COUNTDATE",
    "FISHCOUNT",
    "SPECIESID",
    "COUNTLOCATIONID",
    "COUNTLOCATION",
    "SPECIES"
  ],
  "DATA": [
    [
      2014,
      "June, 18 2014 00:00:00",
      0,
      420,
      2606,
      "Igushik River",
      "Sockeye"
    ],
    [
      2014,
      "June, 19 2014 00:00:00",
      0,
      420,
      2606,
      "Igushik River",
      "Sockeye"
    ],
    [
      2014,
      "June, 20 2014 00:00:00",
      0,
      420,
      2606,
      "Igushik River",
      "Sockeye"
    ],
    [
      2014,
      "June, 21 2014 00:00:00",
      96,
      420,
      2606,
      "Igushik River",
      "Sockeye"
    ],
    [
      2014,
      "June, 22 2014 00:00:00",
      60,
      420,
      2606,
      "Igushik River",
      "Sockeye"
    ],
    [
      2014,
      "June, 23 2014 00:00:00",
      18,
      420,
      2606,
      "Igushik River",
      "Sockeye"
    ],
    [
      2014,
      "June, 24 2014 00:00:00",
      60,
      420,
      2606,
      "Igushik River",
      "Sockeye"
    ],
    [
      2014,
      "June, 25 2014 00:00:00",
      114,
      420,
      2606,
      "Igushik River",
      "Sockeye"
    ],
    [
      2014,
      "June, 26 2014 00:00:00",
      12,
      420,
      2606,
      "Igushik River",
      "Sockeye"
    ],
    [
      2014,
      "June, 27 2014 00:00:00",
      540,
      420,
      2606,
      "Igushik River",
      "Sockeye"
    ],
    [
      2014,
      "June, 28 2014 00:00:00",
      16488,
      420,
      2606,
      "Igushik River",
      "Sockeye"
    ],
    [
      2014,
      "June, 29 2014 00:00:00",
      27774,
      420,
      2606,
      "Igushik River",
      "Sockeye"
    ],
    [
      2014,
      "June, 30 2014 00:00:00",
      20676,
      420,
      2606,
      "Igushik River",
      "Sockeye"
    ],
    [
      2014,
      "July, 01 2014 00:00:00",
      21636,
      420,
      2606,
      "Igushik River",
      "Sockeye"
    ],
    [
      2014,
      "July, 02 2014 00:00:00",
      16428,
      420,
      2606,
      "Igushik River",
      "Sockeye"
    ],
    [
      2014,
      "July, 03 2014 00:00:00",
      15936,
      420,
      2606,
      "Igushik River",
      "Sockeye"
    ],
    [
      2014,
      "July, 04 2014 00:00:00",
      8226,
      420,
      2606,
      "Igushik River",
      "Sockeye"
    ],
    [
      2014,
      "July, 05 2014 00:00:00",
      7044,
      420,
      2606,
      "Igushik River",
      "Sockeye"
    ],
    [
      2014,
      "July, 06 2014 00:00:00",
      10056,
      420,
      2606,
      "Igushik River",
      "Sockeye"
    ],
    [
      2014,
      "July, 07 2014 00:00:00",
      10362,
      420,
      2606,
      "Igushik River",
      "Sockeye"
    ],
    [
      2014,
      "July, 08 2014 00:00:00",
      8586,
      420,
      2606,
      "Igushik River",
      "Sockeye"
    ],
    [
      2014,
      "July, 09 2014 00:00:00",
      14982,
      420,
      2606,
      "Igushik River",
      "Sockeye"
    ],
    [
      2014,
      "July, 10 2014 00:00:00",
      10470,
      420,
      2606,
      "Igushik River",
      "Sockeye"
    ],
    [
      2014,
      "July, 11 2014 00:00:00",
      11094,
      420,
      2606,
      "Igushik River",
      "Sockeye"
    ],
    [
      2014,
      "July, 12 2014 00:00:00",
      9726,
      420,
      2606,
      "Igushik River",
      "Sockeye"
    ],
    [
      2014,
      "July, 13 2014 00:00:00",
      8214,
      420,
      2606,
      "Igushik River",
      "Sockeye"
    ],
    [
      2014,
      "July, 14 2014 00:00:00",
      11964,
      420,
      2606,
      "Igushik River",
      "Sockeye"
    ],
    [
      2014,
      "July, 15 2014 00:00:00",
      17628,
      420,
      2606,
      "Igushik River",
      "Sockeye"
    ],
    [
      2014,
      "July, 16 2014 00:00:00",
      13428,
      420,
      2606,
      "Igushik River",
      "Sockeye"
    ],
    [
      2014,
      "July, 17 2014 00:00:00",
      12042,
      420,
      2606,
      "Igushik River",
      "Sockeye"
    ],
    [
      2014,
      "July, 18 2014 00:00:00",
      9534,
      420,
      2606,
      "Igushik River",
      "Sockeye"
    ],
    [
      2014,
      "July, 19 2014 00:00:00",
      11940,
      420,
      2606,
      "Igushik River",
      "Sockeye"
    ],
    [
      2014,
      "July, 20 2014 00:00:00",
      10542,
      420,
      2606,
      "Igushik River",
      "Sockeye"
    ],
    [
      2014,
      "July, 21 2014 00:00:00",
      9918,
      420,
      2606,
      "Igushik River",
      "Sockeye"
    ],
    [
      2014,
      "July, 22 2014 00:00:00",
      7482,
      420,
      2606,
      "Igushik River",
      "Sockeye"
    ],
    [
      2014,
      "July, 23 2014 00:00:00",
      9564,
      420,
      2606,
      "Igushik River",
      "Sockeye"
    ],
    [
      2014,
      "July, 24 2014 00:00:00",
      7950,
      420,
      2606,
      "Igushik River",
      "Sockeye"
    ]
  ],
  "metadata": {
    "location_id": 2606,
    "species_id": "410",
    "year": "2014",
    "totalRecords": 37,
    "totalCount": 340590,
    "source": "SASAP",
    "last_updated": "2025-10-02T17:53:46.892399"
  }
}