{
  "COLUMNS": [
    "YEAR",
    "COUNTDATE",
    "FISHCOUNT",
    "SPECIESID",
    "COUNTLOCATIONID",
    "COUNTLOCATION",
    "SPECIES"
  ],
  "DATA": [
    [
      2016,
      "2016-06-16",
      0,
      420,
      2501,
      "Anvik River",
      "Pink"
    ],
    [
      2016,
      "2016-06-17",
      0,
      420,
      2501,
      "Anvik River",
      "Pink"
    ],
    [
      2016,
      "2016-06-18",
      0,
      420,
      2501,
      "Anvik River",
      "Pink"
    ],
    [
      2016,
      "2016-06-19",
      0,
      420,
      2501,
      "Anvik River",
      "Pink"
    ],
    [
      2016,
      "2016-06-20",
      0,
      420,
      2501,
      "Anvik River",
      "Pink"
    ],
    [
      2016,
      "2016-06-21",
      0,
      420,
      2501,
      "Anvik River",
      "Pink"
    ],
    [
      2016,
      "2016-06-22",
      0,
      420,
      2501,
      "Anvik River",
      "Pink"
    ],
    [
      2016,
      "2016-06-23",
      0,
      420,
      2501,
      "Anvik River",
      "Pink"
    ],
    [
      2016,
      "2016-06-24",
      0,
      420,
      2501,
      "Anvik River",
      "Pink"
    ],
    [
      2016,
      "2016-06-25",
      0,
      420,
      2501,
      "Anvik River",
      "Pink"
    ],
    [
      2016,
      "2016-06-26",
      37,
      420,
      2501,
      "Anvik River",
      "Pink"
    ],
    [
      2016,
      "2016-06-27",
      27,
      420,
      2501,
      "Anvik River",
      "Pink"
    ],
    [
      2016,
      "2016-06-28",
      41,
      420,
      2501,
      "Anvik River",
      "Pink"
    ],
    [
      2016,
      "2016-06-29",
      178,
      420,
      2501,
      "Anvik River",
      "Pink"
    ],
    [
      2016,
      "2016-06-30",
      53,
      420,
      2501,
      "Anvik River",
      "Pink"
    ],
    [
      2016,
      "2016-07-01",
      166,
      420,
      2501,
      "Anvik River",
      "Pink"
    ],
    [
      2016,
      "2016-07-02",
      470,
      420,
      2501,
      "Anvik River",
      "Pink"
    ],
    [
      2016,
      "2016-07-03",
      359,
      420,
      2501,
      "Anvik River",
      "Pink"
    ],
    [
      2016,
      "2016-07-04",
      920,
      420,
      2501,
      "Anvik River",
      "Pink"
    ],
    [
      2016,
      "2016-07-05",
      1919,
      420,
      2501,
      "Anvik River",
      "Pink"
    ],
    [
      2016,
      "2016-07-06",
      2526,
      420,
      2501,
      "Anvik River",
      "Pink"
    ],
    [
      2016,
      "2016-07-07",
      5680,
      420,
      2501,
      "Anvik River",
      "Pink"
    ],
    [
      2016,
      "2016-07-08",
      6954,
      420,
      2501,
      "Anvik River",
      "Pink"
    ],
    [
      2016,
      "2016-07-09",
      9097,
      420,
      2501,
      "Anvik River",
      "Pink"
    ],
    [
      2016,
      "2016-07-10",
      16737,
      420,
      2501,
      "Anvik River",
      "Pink"
    ],
    [
      2016,
      "2016-07-11",
      19791,
      420,
      2501,
      "Anvik River",
      "Pink"
    ],
    [
      2016,
      "2016-07-12",
      22646,
      420,
      2501,
      "Anvik River",
      "Pink"
    ],
    [
      2016,
      "2016-07-13",
      42650,
      420,
      2501,
      "Anvik River",
      "Pink"
    ],
    [
      2016,
      "2016-07-14",
      37073,
      420,
      2501,
      "Anvik River",
      "Pink"
    ],
    [
      2016,
      "2016-07-15",
      32005,
      420,
      2501,
      "Anvik River",
      "Pink"
    ],
    [
      2016,
      "2016-07-16",
      21658,
      420,
      2501,
      "Anvik River",
      "Pink"
    ],
    [
      2016,
      "2016-07-17",
      26888,
      420,
      2501,
      "Anvik River",
      "Pink"
    ],
    [
      2016,
      "2016-07-18",
      31248,
      420,
      2501,
      "Anvik River",
      "Pink"
    ],
    [
      2016,
      "2016-07-19",
      27293,
      420,
      2501,
      "Anvik River",
      "Pink"
    ],
    [
      2016,
      "2016-07-20",
      20080,
      420,
      2501,
      "Anvik River",
      "Pink"
    ],
    [
      2016,
      "2016-07-21",
      29660,
      420,
      2501,
      "Anvik River",
      "Pink"
    ],
    [
      2016,
      "2016-07-22",
      47131,
      420,
      2501,
      "Anvik River",
      "Pink"
    ],
    [
      2016,
      "2016-07-23",
      41748,
      420,
      2501,
      "Anvik River",
      "Pink"
    ],
    [
      2016,
      "2016-07-24",
      56851,
      420,
      2501,
      "Anvik River",
      "Pink"
    ],
    [
      2016,
      "2016-07-25",
      74319,
      420,
      2501,
      "Anvik River",
      "Pink"
    ],
    [
      2016,
      "2016-07-26",
      91323,
      420,
      2501,
      "Anvik River",
      "Pink"
    ]
  ],
  "metadata": {
    "location_id": 2501,
    "species_id": "420",
    "year": "2016",
    "totalRecords": 41,
    "totalCount": 667528,
    "source": "SASAP",
    "last_updated": "2025-10-02T17:53:45.241253"
  }
}