{
  "COLUMNS": [
    "YEAR",
    "COUNTDATE",
    "FISHCOUNT",
    "SPECIESID",
    "COUNTLOCATIONID",
    "COUNTLOCATION",
    "SPECIES"
  ],
  "DATA": [
    [
      2005,
      "2005-08-31",
      2,
      450,
      2171,
      "Duck Creek",
      "Chum"
    ],
    [
      2005,
      "2005-09-17",
      1,
      450,
      2171,
      "Duck Creek",
      "Chum"
    ],
    [
      2005,
      "2005-09-19",
      1,
      450,
      2171,
      "Duck Creek",
      "Chum"
    ]
  ],
  "metadata": {
    "location_id": 2171,
    "species_id": "450",
    "year": "2005",
    "totalRecords": 3,
    "totalCount": 4,
    "source": "SASAP",
    "last_updated": "2025-10-02T17:53:45.341324"
  }
}