{
  "COLUMNS": [
    "YEAR",
    "COUNTDATE",
    "FISHCOUNT",
    "SPECIESID",
    "COUNTLOCATIONID",
    "COUNTLOCATION",
    "SPECIES"
  ],
  "DATA": [
    [
      1978,
      "1978-06-28",
      0,
      420,
      2142,
      "Crescent Lake",
      "Sockeye"
    ],
    [
      1978,
      "1978-06-29",
      4,
      420,
      2142,
      "Crescent Lake",
      "Sockeye"
    ],
    [
      1978,
      "1978-06-30",
      2,
      420,
      2142,
      "Crescent Lake",
      "Sockeye"
    ],
    [
      1978,
      "1978-07-01",
      5,
      420,
      2142,
      "Crescent Lake",
      "Sockeye"
    ],
    [
      1978,
      "1978-07-02",
      3,
      420,
      2142,
      "Crescent Lake",
      "Sockeye"
    ],
    [
      1978,
      "1978-07-03",
      18,
      420,
      2142,
      "Crescent Lake",
      "Sockeye"
    ],
    [
      1978,
      "1978-07-04",
      0,
      420,
      2142,
      "Crescent Lake",
      "Sockeye"
    ],
    [
      1978,
      "1978-07-05",
      79,
      420,
      2142,
      "Crescent Lake",
      "Sockeye"
    ],
    [
      1978,
      "1978-07-06",
      34,
      420,
      2142,
      "Crescent Lake",
      "Sockeye"
    ],
    [
      1978,
      "1978-07-07",
      27,
      420,
      2142,
      "Crescent Lake",
      "Sockeye"
    ],
    [
      1978,
      "1978-07-08",
      11,
      420,
      2142,
      "Crescent Lake",
      "Sockeye"
    ],
    [
      1978,
      "1978-07-09",
      22,
      420,
      2142,
      "Crescent Lake",
      "Sockeye"
    ],
    [
      1978,
      "1978-07-10",
      20,
      420,
      2142,
      "Crescent Lake",
      "Sockeye"
    ],
    [
      1978,
      "1978-07-11",
      51,
      420,
      2142,
      "Crescent Lake",
      "Sockeye"
    ],
    [
      1978,
      "1978-07-12",
      35,
      420,
      2142,
      "Crescent Lake",
      "Sockeye"
    ],
    [
      1978,
      "1978-07-13",
      13,
      420,
      2142,
      "Crescent Lake",
      "Sockeye"
    ],
    [
      1978,
      "1978-07-14",
      4,
      420,
      2142,
      "Crescent Lake",
      "Sockeye"
    ],
    [
      1978,
      "1978-07-15",
      0,
      420,
      2142,
      "Crescent Lake",
      "Sockeye"
    ],
    [
      1978,
      "1978-07-16",
      1,
      420,
      2142,
      "Crescent Lake",
      "Sockeye"
    ],
    [
      1978,
      "1978-07-17",
      10,
      420,
      2142,
      "Crescent Lake",
      "Sockeye"
    ],
    [
      1978,
      "1978-07-18",
      11,
      420,
      2142,
      "Crescent Lake",
      "Sockeye"
    ],
    [
      1978,
      "1978-07-19",
      14,
      420,
      2142,
      "Crescent Lake",
      "Sockeye"
    ],
    [
      1978,
      "1978-07-20",
      17,
      420,
      2142,
      "Crescent Lake",
      "Sockeye"
    ],
    [
      1978,
      "1978-07-21",
      16,
      420,
      2142,
      "Crescent Lake",
      "Sockeye"
    ],
    [
      1978,
      "1978-07-22",
      24,
      420,
      2142,
      "Crescent Lake",
      "Sockeye"
    ],
    [
      1978,
      "1978-07-23",
      21,
      420,
      2142,
      "Crescent Lake",
      "Sockeye"
    ],
    [
      1978,
      "1978-07-24",
      1,
      420,
      2142,
      "Crescent Lake",
      "Sockeye"
    ],
    [
      1978,
      "1978-07-25",
      14,
      420,
      2142,
      "Crescent Lake",
      "Sockeye"
    ],
    [
      1978,
      "1978-07-26",
      62,
      420,
      2142,
      "Crescent Lake",
      "Sockeye"
    ],
    [
      1978,
      "1978-07-27",
      74,
      420,
      2142,
      "Crescent Lake",
      "Sockeye"
    ],
    [
      1978,
      "1978-07-28",
      67,
      420,
      2142,
      "Crescent Lake",
      "Sockeye"
    ],
    [
      1978,
      "1978-07-29",
      89,
      420,
      2142,
      "Crescent Lake",
      "Sockeye"
    ],
    [
      1978,
      "1978-07-30",
      113,
      420,
      2142,
      "Crescent Lake",
      "Sockeye"
    ],
    [
      1978,
      "1978-07-31",
      73,
      420,
      2142,
      "Crescent Lake",
      "Sockeye"
    ],
    [
      1978,
      "1978-08-01",
      30,
      420,
      2142,
      "Crescent Lake",
      "Sockeye"
    ],
    [
      1978,
      "1978-08-02",
      12,
      420,
      2142,
      "Crescent Lake",
      "Sockeye"
    ],
    [
      1978,
      "1978-08-03",
      4,
      420,
      2142,
      "Crescent Lake",
      "Sockeye"
    ],
    [
      1978,
      "1978-08-04",
      11,
      420,
      2142,
      "Crescent Lake",
      "Sockeye"
    ],
    [
      1978,
      "1978-08-05",
      1,
      420,
      2142,
      "Crescent Lake",
      "Sockeye"
    ],
    [
      1978,
      "1978-08-06",
      7,
      420,
      2142,
      "Crescent Lake",
      "Sockeye"
    ],
    [
      1978,
      "1978-08-07",
      8,
      420,
      2142,
      "Crescent Lake",
      "Sockeye"
    ],
    [
      1978,
      "1978-08-08",
      12,
      420,
      2142,
      "Crescent Lake",
      "Sockeye"
    ],
    [
      1978,
      "1978-08-09",
      6,
      420,
      2142,
      "Crescent Lake",
      "Sockeye"
    ],
    [
      1978,
      "1978-08-10",
      2,
      420,
      2142,
      "Crescent Lake",
      "Sockeye"
    ],
    [
      1978,
      "1978-08-11",
      5,
      420,
      2142,
      "Crescent Lake",
      "Sockeye"
    ],
    [
      1978,
      "1978-08-12",
      7,
      420,
      2142,
      "Crescent Lake",
      "Sockeye"
    ],
    [
      1978,
      "1978-08-13",
      4,
      420,
      2142,
      "Crescent Lake",
      "Sockeye"
    ]
  ],
  "metadata": {
    "location_id": 2142,
    "species_id": "410",
    "year": "1978",
    "totalRecords": 47,
    "totalCount": 1044,
    "source": "SASAP",
    "last_updated": "2025-10-02T17:53:42.769930"
  }
}