{
  "COLUMNS": [
    "YEAR",
    "COUNTDATE",
    "FISHCOUNT",
    "SPECIESID",
    "COUNTLOCATIONID",
    "COUNTLOCATION",
    "SPECIES"
  ],
  "DATA": [
    [
      1987,
      "August, 01 1987 00:00:00",
      415,
      420,
      2139,
      "Nakina River",
      "Pink"
    ],
    [
      1987,
      "August, 02 1987 00:00:00",
      1127,
      420,
      2139,
      "Nakina River",
      "Pink"
    ],
    [
      1987,
      "August, 03 1987 00:00:00",
      1602,
      420,
      2139,
      "Nakina River",
      "Pink"
    ],
    [
      1987,
      "August, 04 1987 00:00:00",
      2281,
      420,
      2139,
      "Nakina River",
      "Pink"
    ],
    [
      1987,
      "August, 05 1987 00:00:00",
      2314,
      420,
      2139,
      "Nakina River",
      "Pink"
    ],
    [
      1987,
      "August, 06 1987 00:00:00",
      2471,
      420,
      2139,
      "Nakina River",
      "Pink"
    ],
    [
      1987,
      "August, 07 1987 00:00:00",
      2434,
      420,
      2139,
      "Nakina River",
      "Pink"
    ],
    [
      1987,
      "August, 08 1987 00:00:00",
      2572,
      420,
      2139,
      "Nakina River",
      "Pink"
    ],
    [
      1987,
      "August, 09 1987 00:00:00",
      2528,
      420,
      2139,
      "Nakina River",
      "Pink"
    ],
    [
      1987,
      "August, 10 1987 00:00:00",
      2377,
      420,
      2139,
      "Nakina River",
      "Pink"
    ],
    [
      1987,
      "August, 11 1987 00:00:00",
      1846,
      420,
      2139,
      "Nakina River",
      "Pink"
    ],
    [
      1987,
      "August, 12 1987 00:00:00",
      2044,
      420,
      2139,
      "Nakina River",
      "Pink"
    ],
    [
      1987,
      "August, 13 1987 00:00:00",
      1410,
      420,
      2139,
      "Nakina River",
      "Pink"
    ],
    [
      1987,
      "August, 14 1987 00:00:00",
      1257,
      420,
      2139,
      "Nakina River",
      "Pink"
    ],
    [
      1987,
      "August, 15 1987 00:00:00",
      1018,
      420,
      2139,
      "Nakina River",
      "Pink"
    ],
    [
      1987,
      "August, 16 1987 00:00:00",
      778,
      420,
      2139,
      "Nakina River",
      "Pink"
    ],
    [
      1987,
      "August, 17 1987 00:00:00",
      516,
      420,
      2139,
      "Nakina River",
      "Pink"
    ],
    [
      1987,
      "August, 18 1987 00:00:00",
      449,
      420,
      2139,
      "Nakina River",
      "Pink"
    ],
    [
      1987,
      "August, 19 1987 00:00:00",
      319,
      420,
      2139,
      "Nakina River",
      "Pink"
    ],
    [
      1987,
      "August, 20 1987 00:00:00",
      274,
      420,
      2139,
      "Nakina River",
      "Pink"
    ],
    [
      1987,
      "August, 21 1987 00:00:00",
      161,
      420,
      2139,
      "Nakina River",
      "Pink"
    ],
    [
      1987,
      "August, 22 1987 00:00:00",
      139,
      420,
      2139,
      "Nakina River",
      "Pink"
    ]
  ],
  "metadata": {
    "location_id": 2139,
    "species_id": "420",
    "year": "1987",
    "totalRecords": 22,
    "totalCount": 30332,
    "source": "SASAP",
    "last_updated": "2025-10-02T17:53:44.301838"
  }
}