{
  "COLUMNS": [
    "YEAR",
    "COUNTDATE",
    "FISHCOUNT",
    "SPECIESID",
    "COUNTLOCATIONID",
    "COUNTLOCATION",
    "SPECIES"
  ],
  "DATA": [
    [
      2003,
      "2003-08-16",
      1,
      440,
      2115,
      "Neva Creek",
      "Coho"
    ],
    [
      2003,
      "2003-08-17",
      1,
      440,
      2115,
      "Neva Creek",
      "Coho"
    ],
    [
      2003,
      "2003-08-30",
      43,
      440,
      2115,
      "Neva Creek",
      "Coho"
    ],
    [
      2003,
      "2003-08-31",
      71,
      440,
      2115,
      "Neva Creek",
      "Coho"
    ],
    [
      2003,
      "2003-09-01",
      20,
      440,
      2115,
      "Neva Creek",
      "Coho"
    ],
    [
      2003,
      "2003-09-02",
      140,
      440,
      2115,
      "Neva Creek",
      "Coho"
    ],
    [
      2003,
      "2003-09-03",
      84,
      440,
      2115,
      "Neva Creek",
      "Coho"
    ],
    [
      2003,
      "2003-09-04",
      35,
      440,
      2115,
      "Neva Creek",
      "Coho"
    ],
    [
      2003,
      "2003-09-05",
      26,
      440,
      2115,
      "Neva Creek",
      "Coho"
    ],
    [
      2003,
      "2003-09-06",
      25,
      440,
      2115,
      "Neva Creek",
      "Coho"
    ],
    [
      2003,
      "2003-09-07",
      20,
      440,
      2115,
      "Neva Creek",
      "Coho"
    ],
    [
      2003,
      "2003-09-08",
      56,
      440,
      2115,
      "Neva Creek",
      "Coho"
    ],
    [
      2003,
      "2003-09-09",
      114,
      440,
      2115,
      "Neva Creek",
      "Coho"
    ],
    [
      2003,
      "2003-09-10",
      127,
      440,
      2115,
      "Neva Creek",
      "Coho"
    ],
    [
      2003,
      "2003-09-11",
      25,
      440,
      2115,
      "Neva Creek",
      "Coho"
    ],
    [
      2003,
      "2003-09-12",
      34,
      440,
      2115,
      "Neva Creek",
      "Coho"
    ],
    [
      2003,
      "2003-09-13",
      225,
      440,
      2115,
      "Neva Creek",
      "Coho"
    ],
    [
      2003,
      "2003-09-14",
      81,
      440,
      2115,
      "Neva Creek",
      "Coho"
    ],
    [
      2003,
      "2003-09-15",
      64,
      440,
      2115,
      "Neva Creek",
      "Coho"
    ],
    [
      2003,
      "2003-09-16",
      20,
      440,
      2115,
      "Neva Creek",
      "Coho"
    ],
    [
      2003,
      "2003-09-17",
      15,
      440,
      2115,
      "Neva Creek",
      "Coho"
    ],
    [
      2003,
      "2003-09-18",
      11,
      440,
      2115,
      "Neva Creek",
      "Coho"
    ],
    [
      2003,
      "2003-09-19",
      5,
      440,
      2115,
      "Neva Creek",
      "Coho"
    ],
    [
      2003,
      "2003-09-20",
      26,
      440,
      2115,
      "Neva Creek",
      "Coho"
    ],
    [
      2003,
      "2003-09-21",
      37,
      440,
      2115,
      "Neva Creek",
      "Coho"
    ],
    [
      2003,
      "2003-09-22",
      8,
      440,
      2115,
      "Neva Creek",
      "Coho"
    ],
    [
      2003,
      "2003-09-23",
      7,
      440,
      2115,
      "Neva Creek",
      "Coho"
    ],
    [
      2003,
      "2003-09-24",
      45,
      440,
      2115,
      "Neva Creek",
      "Coho"
    ],
    [
      2003,
      "2003-09-25",
      85,
      440,
      2115,
      "Neva Creek",
      "Coho"
    ],
    [
      2003,
      "2003-09-26",
      22,
      440,
      2115,
      "Neva Creek",
      "Coho"
    ],
    [
      2003,
      "2003-09-27",
      79,
      440,
      2115,
      "Neva Creek",
      "Coho"
    ],
    [
      2003,
      "2003-09-28",
      27,
      440,
      2115,
      "Neva Creek",
      "Coho"
    ],
    [
      2003,
      "2003-09-29",
      22,
      440,
      2115,
      "Neva Creek",
      "Coho"
    ],
    [
      2003,
      "2003-09-30",
      23,
      440,
      2115,
      "Neva Creek",
      "Coho"
    ],
    [
      2003,
      "2003-10-01",
      23,
      440,
      2115,
      "Neva Creek",
      "Coho"
    ],
    [
      2003,
      "2003-10-02",
      18,
      440,
      2115,
      "Neva Creek",
      "Coho"
    ],
    [
      2003,
      "2003-10-03",
      4,
      440,
      2115,
      "Neva Creek",
      "Coho"
    ],
    [
      2003,
      "2003-10-04",
      4,
      440,
      2115,
      "Neva Creek",
      "Coho"
    ],
    [
      2003,
      "2003-10-05",
      4,
      440,
      2115,
      "Neva Creek",
      "Coho"
    ],
    [
      2003,
      "2003-10-06",
      2,
      440,
      2115,
      "Neva Creek",
      "Coho"
    ],
    [
      2003,
      "2003-10-07",
      3,
      440,
      2115,
      "Neva Creek",
      "Coho"
    ],
    [
      2003,
      "2003-10-08",
      9,
      440,
      2115,
      "Neva Creek",
      "Coho"
    ]
  ],
  "metadata": {
    "location_id": 2115,
    "species_id": "440",
    "year": "2003",
    "totalRecords": 42,
    "totalCount": 1691,
    "source": "SASAP",
    "last_updated": "2025-10-02T17:53:45.534866"
  }
}