{
  "COLUMNS": [
    "YEAR",
    "COUNTDATE",
    "FISHCOUNT",
    "SPECIESID",
    "COUNTLOCATIONID",
    "COUNTLOCATION",
    "SPECIES"
  ],
  "DATA": [
    [
      1971,
      "July, 06 1971 00:00:00",
      0,
      420,
      2123,
      "Kadashan West",
      "Pink"
    ],
    [
      1971,
      "July, 07 1971 00:00:00",
      0,
      420,
      2123,
      "Kadashan West",
      "Pink"
    ],
    [
      1971,
      "July, 08 1971 00:00:00",
      0,
      420,
      2123,
      "Kadashan West",
      "Pink"
    ],
    [
      1971,
      "July, 09 1971 00:00:00",
      0,
      420,
      2123,
      "Kadashan West",
      "Pink"
    ],
    [
      1971,
      "July, 10 1971 00:00:00",
      0,
      420,
      2123,
      "Kadashan West",
      "Pink"
    ],
    [
      1971,
      "July, 11 1971 00:00:00",
      0,
      420,
      2123,
      "Kadashan West",
      "Pink"
    ],
    [
      1971,
      "July, 12 1971 00:00:00",
      0,
      420,
      2123,
      "Kadashan West",
      "Pink"
    ],
    [
      1971,
      "July, 13 1971 00:00:00",
      0,
      420,
      2123,
      "Kadashan West",
      "Pink"
    ],
    [
      1971,
      "July, 14 1971 00:00:00",
      0,
      420,
      2123,
      "Kadashan West",
      "Pink"
    ],
    [
      1971,
      "July, 15 1971 00:00:00",
      0,
      420,
      2123,
      "Kadashan West",
      "Pink"
    ],
    [
      1971,
      "July, 16 1971 00:00:00",
      887,
      420,
      2123,
      "Kadashan West",
      "Pink"
    ],
    [
      1971,
      "July, 17 1971 00:00:00",
      20,
      420,
      2123,
      "Kadashan West",
      "Pink"
    ],
    [
      1971,
      "July, 18 1971 00:00:00",
      165,
      420,
      2123,
      "Kadashan West",
      "Pink"
    ],
    [
      1971,
      "July, 19 1971 00:00:00",
      513,
      420,
      2123,
      "Kadashan West",
      "Pink"
    ],
    [
      1971,
      "July, 20 1971 00:00:00",
      1985,
      420,
      2123,
      "Kadashan West",
      "Pink"
    ],
    [
      1971,
      "July, 21 1971 00:00:00",
      145,
      420,
      2123,
      "Kadashan West",
      "Pink"
    ],
    [
      1971,
      "July, 22 1971 00:00:00",
      72,
      420,
      2123,
      "Kadashan West",
      "Pink"
    ],
    [
      1971,
      "July, 23 1971 00:00:00",
      73,
      420,
      2123,
      "Kadashan West",
      "Pink"
    ],
    [
      1971,
      "July, 24 1971 00:00:00",
      773,
      420,
      2123,
      "Kadashan West",
      "Pink"
    ],
    [
      1971,
      "July, 25 1971 00:00:00",
      302,
      420,
      2123,
      "Kadashan West",
      "Pink"
    ],
    [
      1971,
      "July, 26 1971 00:00:00",
      72,
      420,
      2123,
      "Kadashan West",
      "Pink"
    ],
    [
      1971,
      "July, 27 1971 00:00:00",
      293,
      420,
      2123,
      "Kadashan West",
      "Pink"
    ],
    [
      1971,
      "July, 28 1971 00:00:00",
      357,
      420,
      2123,
      "Kadashan West",
      "Pink"
    ],
    [
      1971,
      "July, 29 1971 00:00:00",
      641,
      420,
      2123,
      "Kadashan West",
      "Pink"
    ],
    [
      1971,
      "July, 30 1971 00:00:00",
      198,
      420,
      2123,
      "Kadashan West",
      "Pink"
    ],
    [
      1971,
      "July, 31 1971 00:00:00",
      640,
      420,
      2123,
      "Kadashan West",
      "Pink"
    ],
    [
      1971,
      "August, 01 1971 00:00:00",
      260,
      420,
      2123,
      "Kadashan West",
      "Pink"
    ],
    [
      1971,
      "August, 02 1971 00:00:00",
      41706,
      420,
      2123,
      "Kadashan West",
      "Pink"
    ],
    [
      1971,
      "August, 03 1971 00:00:00",
      91,
      420,
      2123,
      "Kadashan West",
      "Pink"
    ],
    [
      1971,
      "August, 04 1971 00:00:00",
      55,
      420,
      2123,
      "Kadashan West",
      "Pink"
    ],
    [
      1971,
      "August, 05 1971 00:00:00",
      15,
      420,
      2123,
      "Kadashan West",
      "Pink"
    ],
    [
      1971,
      "August, 06 1971 00:00:00",
      0,
      420,
      2123,
      "Kadashan West",
      "Pink"
    ],
    [
      1971,
      "August, 07 1971 00:00:00",
      928,
      420,
      2123,
      "Kadashan West",
      "Pink"
    ],
    [
      1971,
      "August, 08 1971 00:00:00",
      5,
      420,
      2123,
      "Kadashan West",
      "Pink"
    ],
    [
      1971,
      "August, 09 1971 00:00:00",
      406,
      420,
      2123,
      "Kadashan West",
      "Pink"
    ],
    [
      1971,
      "August, 10 1971 00:00:00",
      350,
      420,
      2123,
      "Kadashan West",
      "Pink"
    ],
    [
      1971,
      "August, 11 1971 00:00:00",
      553,
      420,
      2123,
      "Kadashan West",
      "Pink"
    ],
    [
      1971,
      "August, 12 1971 00:00:00",
      281,
      420,
      2123,
      "Kadashan West",
      "Pink"
    ],
    [
      1971,
      "August, 13 1971 00:00:00",
      472,
      420,
      2123,
      "Kadashan West",
      "Pink"
    ],
    [
      1971,
      "August, 14 1971 00:00:00",
      776,
      420,
      2123,
      "Kadashan West",
      "Pink"
    ],
    [
      1971,
      "August, 15 1971 00:00:00",
      785,
      420,
      2123,
      "Kadashan West",
      "Pink"
    ],
    [
      1971,
      "August, 16 1971 00:00:00",
      290,
      420,
      2123,
      "Kadashan West",
      "Pink"
    ],
    [
      1971,
      "August, 17 1971 00:00:00",
      820,
      420,
      2123,
      "Kadashan West",
      "Pink"
    ],
    [
      1971,
      "August, 18 1971 00:00:00",
      765,
      420,
      2123,
      "Kadashan West",
      "Pink"
    ],
    [
      1971,
      "August, 19 1971 00:00:00",
      1866,
      420,
      2123,
      "Kadashan West",
      "Pink"
    ]
  ],
  "metadata": {
    "location_id": 2123,
    "species_id": "420",
    "year": "1971",
    "totalRecords": 45,
    "totalCount": 57560,
    "source": "SASAP",
    "last_updated": "2025-10-02T17:53:45.573412"
  }
}