{
  "COLUMNS": [
    "YEAR",
    "COUNTDATE",
    "FISHCOUNT",
    "SPECIESID",
    "COUNTLOCATIONID",
    "COUNTLOCATION",
    "SPECIES"
  ],
  "DATA": [
    [
      1985,
      "1985-07-16",
      2,
      420,
      2105,
      "Redoubt Lake",
      "Pink"
    ],
    [
      1985,
      "1985-07-18",
      5,
      420,
      2105,
      "Redoubt Lake",
      "Pink"
    ],
    [
      1985,
      "1985-07-20",
      2,
      420,
      2105,
      "Redoubt Lake",
      "Pink"
    ],
    [
      1985,
      "1985-07-21",
      3,
      420,
      2105,
      "Redoubt Lake",
      "Pink"
    ],
    [
      1985,
      "1985-07-22",
      9,
      420,
      2105,
      "Redoubt Lake",
      "Pink"
    ],
    [
      1985,
      "1985-07-23",
      5,
      420,
      2105,
      "Redoubt Lake",
      "Pink"
    ],
    [
      1985,
      "1985-07-24",
      6,
      420,
      2105,
      "Redoubt Lake",
      "Pink"
    ],
    [
      1985,
      "1985-07-25",
      12,
      420,
      2105,
      "Redoubt Lake",
      "Pink"
    ],
    [
      1985,
      "1985-07-26",
      11,
      420,
      2105,
      "Redoubt Lake",
      "Pink"
    ],
    [
      1985,
      "1985-07-27",
      18,
      420,
      2105,
      "Redoubt Lake",
      "Pink"
    ],
    [
      1985,
      "1985-07-28",
      5,
      420,
      2105,
      "Redoubt Lake",
      "Pink"
    ],
    [
      1985,
      "1985-07-29",
      14,
      420,
      2105,
      "Redoubt Lake",
      "Pink"
    ],
    [
      1985,
      "1985-07-30",
      18,
      420,
      2105,
      "Redoubt Lake",
      "Pink"
    ],
    [
      1985,
      "1985-07-31",
      24,
      420,
      2105,
      "Redoubt Lake",
      "Pink"
    ],
    [
      1985,
      "1985-08-01",
      37,
      420,
      2105,
      "Redoubt Lake",
      "Pink"
    ],
    [
      1985,
      "1985-08-02",
      26,
      420,
      2105,
      "Redoubt Lake",
      "Pink"
    ],
    [
      1985,
      "1985-08-03",
      53,
      420,
      2105,
      "Redoubt Lake",
      "Pink"
    ],
    [
      1985,
      "1985-08-04",
      51,
      420,
      2105,
      "Redoubt Lake",
      "Pink"
    ],
    [
      1985,
      "1985-08-05",
      116,
      420,
      2105,
      "Redoubt Lake",
      "Pink"
    ],
    [
      1985,
      "1985-08-06",
      22,
      420,
      2105,
      "Redoubt Lake",
      "Pink"
    ],
    [
      1985,
      "1985-08-07",
      90,
      420,
      2105,
      "Redoubt Lake",
      "Pink"
    ],
    [
      1985,
      "1985-08-08",
      69,
      420,
      2105,
      "Redoubt Lake",
      "Pink"
    ],
    [
      1985,
      "1985-08-09",
      137,
      420,
      2105,
      "Redoubt Lake",
      "Pink"
    ],
    [
      1985,
      "1985-08-10",
      362,
      420,
      2105,
      "Redoubt Lake",
      "Pink"
    ],
    [
      1985,
      "1985-08-11",
      167,
      420,
      2105,
      "Redoubt Lake",
      "Pink"
    ],
    [
      1985,
      "1985-08-12",
      111,
      420,
      2105,
      "Redoubt Lake",
      "Pink"
    ],
    [
      1985,
      "1985-08-13",
      209,
      420,
      2105,
      "Redoubt Lake",
      "Pink"
    ],
    [
      1985,
      "1985-08-14",
      159,
      420,
      2105,
      "Redoubt Lake",
      "Pink"
    ],
    [
      1985,
      "1985-08-15",
      325,
      420,
      2105,
      "Redoubt Lake",
      "Pink"
    ],
    [
      1985,
      "1985-08-16",
      142,
      420,
      2105,
      "Redoubt Lake",
      "Pink"
    ],
    [
      1985,
      "1985-08-17",
      442,
      420,
      2105,
      "Redoubt Lake",
      "Pink"
    ],
    [
      1985,
      "1985-08-18",
      611,
      420,
      2105,
      "Redoubt Lake",
      "Pink"
    ],
    [
      1985,
      "1985-08-19",
      234,
      420,
      2105,
      "Redoubt Lake",
      "Pink"
    ],
    [
      1985,
      "1985-08-20",
      279,
      420,
      2105,
      "Redoubt Lake",
      "Pink"
    ],
    [
      1985,
      "1985-08-21",
      604,
      420,
      2105,
      "Redoubt Lake",
      "Pink"
    ],
    [
      1985,
      "1985-08-22",
      1215,
      420,
      2105,
      "Redoubt Lake",
      "Pink"
    ],
    [
      1985,
      "1985-08-23",
      620,
      420,
      2105,
      "Redoubt Lake",
      "Pink"
    ],
    [
      1985,
      "1985-08-24",
      1010,
      420,
      2105,
      "Redoubt Lake",
      "Pink"
    ],
    [
      1985,
      "1985-08-25",
      529,
      420,
      2105,
      "Redoubt Lake",
      "Pink"
    ],
    [
      1985,
      "1985-08-26",
      490,
      420,
      2105,
      "Redoubt Lake",
      "Pink"
    ],
    [
      1985,
      "1985-08-27",
      563,
      420,
      2105,
      "Redoubt Lake",
      "Pink"
    ],
    [
      1985,
      "1985-08-28",
      830,
      420,
      2105,
      "Redoubt Lake",
      "Pink"
    ]
  ],
  "metadata": {
    "location_id": 2105,
    "species_id": "420",
    "year": "1985",
    "totalRecords": 42,
    "totalCount": 9637,
    "source": "SASAP",
    "last_updated": "2025-10-02T17:53:40.125162"
  }
}