{
  "COLUMNS": [
    "YEAR",
    "COUNTDATE",
    "FISHCOUNT",
    "SPECIESID",
    "COUNTLOCATIONID",
    "COUNTLOCATION",
    "SPECIES"
  ],
  "DATA": [
    [
      1999,
      "October, 19 1999 00:00:00",
      1,
      480,
      2104,
      "Klawock River",
      "Steelhead trout"
    ]
  ],
  "metadata": {
    "location_id": 2104,
    "species_id": "480",
    "year": "1999",
    "totalRecords": 1,
    "totalCount": 1,
    "source": "SASAP",
    "last_updated": "2025-10-02T17:53:41.714350"
  }
}