{
  "COLUMNS": [
    "YEAR",
    "COUNTDATE",
    "FISHCOUNT",
    "SPECIESID",
    "COUNTLOCATIONID",
    "COUNTLOCATION",
    "SPECIES"
  ],
  "DATA": [
    [
      1982,
      "1982-08-11",
      2,
      450,
      2101,
      "Auke Creek",
      "Chum"
    ],
    [
      1982,
      "1982-08-12",
      1,
      450,
      2101,
      "Auke Creek",
      "Chum"
    ],
    [
      1982,
      "1982-08-16",
      2,
      450,
      2101,
      "Auke Creek",
      "Chum"
    ],
    [
      1982,
      "1982-08-17",
      14,
      450,
      2101,
      "Auke Creek",
      "Chum"
    ],
    [
      1982,
      "1982-08-18",
      37,
      450,
      2101,
      "Auke Creek",
      "Chum"
    ],
    [
      1982,
      "1982-08-19",
      26,
      450,
      2101,
      "Auke Creek",
      "Chum"
    ],
    [
      1982,
      "1982-08-20",
      22,
      450,
      2101,
      "Auke Creek",
      "Chum"
    ],
    [
      1982,
      "1982-08-23",
      32,
      450,
      2101,
      "Auke Creek",
      "Chum"
    ],
    [
      1982,
      "1982-08-24",
      20,
      450,
      2101,
      "Auke Creek",
      "Chum"
    ],
    [
      1982,
      "1982-08-25",
      53,
      450,
      2101,
      "Auke Creek",
      "Chum"
    ],
    [
      1982,
      "1982-08-26",
      50,
      450,
      2101,
      "Auke Creek",
      "Chum"
    ],
    [
      1982,
      "1982-08-27",
      11,
      450,
      2101,
      "Auke Creek",
      "Chum"
    ],
    [
      1982,
      "1982-08-28",
      7,
      450,
      2101,
      "Auke Creek",
      "Chum"
    ],
    [
      1982,
      "1982-08-30",
      6,
      450,
      2101,
      "Auke Creek",
      "Chum"
    ],
    [
      1982,
      "1982-08-31",
      7,
      450,
      2101,
      "Auke Creek",
      "Chum"
    ],
    [
      1982,
      "1982-09-01",
      2,
      450,
      2101,
      "Auke Creek",
      "Chum"
    ],
    [
      1982,
      "1982-09-02",
      1,
      450,
      2101,
      "Auke Creek",
      "Chum"
    ],
    [
      1982,
      "1982-09-03",
      1,
      450,
      2101,
      "Auke Creek",
      "Chum"
    ],
    [
      1982,
      "1982-09-08",
      1,
      450,
      2101,
      "Auke Creek",
      "Chum"
    ],
    [
      1982,
      "1982-09-09",
      1,
      450,
      2101,
      "Auke Creek",
      "Chum"
    ],
    [
      1982,
      "1982-09-10",
      1,
      450,
      2101,
      "Auke Creek",
      "Chum"
    ],
    [
      1982,
      "1982-09-13",
      1,
      450,
      2101,
      "Auke Creek",
      "Chum"
    ]
  ],
  "metadata": {
    "location_id": 2101,
    "species_id": "450",
    "year": "1982",
    "totalRecords": 22,
    "totalCount": 298,
    "source": "SASAP",
    "last_updated": "2025-10-02T17:53:44.451585"
  }
}