{
  "COLUMNS": [
    "YEAR",
    "COUNTDATE",
    "FISHCOUNT",
    "SPECIESID",
    "COUNTLOCATIONID",
    "COUNTLOCATION",
    "SPECIES"
  ],
  "DATA": [
    [
      2013,
      "2013-07-22",
      1,
      450,
      2100,
      "Hugh Smith",
      "Chum"
    ],
    [
      2013,
      "2013-07-27",
      1,
      450,
      2100,
      "Hugh Smith",
      "Chum"
    ],
    [
      2013,
      "2013-08-25",
      1,
      450,
      2100,
      "Hugh Smith",
      "Chum"
    ],
    [
      2013,
      "2013-09-15",
      1,
      450,
      2100,
      "Hugh Smith",
      "Chum"
    ],
    [
      2013,
      "2013-09-17",
      3,
      450,
      2100,
      "Hugh Smith",
      "Chum"
    ],
    [
      2013,
      "2013-09-18",
      1,
      450,
      2100,
      "Hugh Smith",
      "Chum"
    ],
    [
      2013,
      "2013-09-19",
      1,
      450,
      2100,
      "Hugh Smith",
      "Chum"
    ],
    [
      2013,
      "2013-09-20",
      4,
      450,
      2100,
      "Hugh Smith",
      "Chum"
    ],
    [
      2013,
      "2013-09-22",
      1,
      450,
      2100,
      "Hugh Smith",
      "Chum"
    ],
    [
      2013,
      "2013-09-24",
      1,
      450,
      2100,
      "Hugh Smith",
      "Chum"
    ],
    [
      2013,
      "2013-09-25",
      1,
      450,
      2100,
      "Hugh Smith",
      "Chum"
    ],
    [
      2013,
      "2013-09-26",
      2,
      450,
      2100,
      "Hugh Smith",
      "Chum"
    ],
    [
      2013,
      "2013-09-27",
      1,
      450,
      2100,
      "Hugh Smith",
      "Chum"
    ],
    [
      2013,
      "2013-09-29",
      1,
      450,
      2100,
      "Hugh Smith",
      "Chum"
    ],
    [
      2013,
      "2013-09-30",
      2,
      450,
      2100,
      "Hugh Smith",
      "Chum"
    ],
    [
      2013,
      "2013-10-01",
      4,
      450,
      2100,
      "Hugh Smith",
      "Chum"
    ],
    [
      2013,
      "2013-10-02",
      3,
      450,
      2100,
      "Hugh Smith",
      "Chum"
    ],
    [
      2013,
      "2013-10-05",
      1,
      450,
      2100,
      "Hugh Smith",
      "Chum"
    ]
  ],
  "metadata": {
    "location_id": 2100,
    "species_id": "450",
    "year": "2013",
    "totalRecords": 18,
    "totalCount": 30,
    "source": "SASAP",
    "last_updated": "2025-10-02T17:53:45.067760"
  }
}